retryhttp/__init__.py
retryhttp/_constants.py
retryhttp/_retry.py
retryhttp/_types.py
retryhttp/_utils.py
retryhttp/_wait.py
retryhttp/py.typed
retryhttp-1.3.1.dist-info/LICENSE
retryhttp-1.3.1.dist-info/METADATA
retryhttp-1.3.1.dist-info/WHEEL
retryhttp-1.3.1.dist-info/top_level.txt
retryhttp-1.3.1.dist-info/RECORD
