Metadata-Version: 2.2
Name: retryhttp
Version: 1.3.1
Summary: Retry potentially transient HTTP errors in Python.
Author-email: Austin de Coup-Crank <austindcc@gmail.com>
Maintainer-email: Austin de Coup-Crank <austindcc@gmail.com>
License: 
Project-URL: Documentation, https://retryhttp.readthedocs.io
Project-URL: Homepage, https://github.com/austind/retryhttp
Project-URL: Repository, https://github.com/austind/retryhttp.git
Project-URL: Issues, https://github.com/austind/retryhttp/issues
Classifier: Development Status :: 5 - Production/Stable
Classifier: Intended Audience :: Developers
Classifier: License :: OSI Approved :: Apache Software License
Classifier: Programming Language :: Python
Classifier: Programming Language :: Python :: 3
Classifier: Programming Language :: Python :: 3 :: Only
Classifier: Programming Language :: Python :: 3.8
Classifier: Programming Language :: Python :: 3.9
Classifier: Programming Language :: Python :: 3.10
Classifier: Programming Language :: Python :: 3.11
Classifier: Programming Language :: Python :: 3.12
Classifier: Topic :: Internet :: WWW/HTTP
Classifier: Topic :: Utilities
Requires-Python: >=3.8
License-File: LICENSE
Requires-Dist: httpx
Requires-Dist: pydantic
Requires-Dist: requests
Requires-Dist: types-requests
Requires-Dist: tenacity
Provides-Extra: httpx
Requires-Dist: httpx; extra == "httpx"
Requires-Dist: tenacity; extra == "httpx"
Provides-Extra: requests
Requires-Dist: requests; extra == "requests"
Requires-Dist: types-requests; extra == "requests"
Requires-Dist: tenacity; extra == "requests"
Provides-Extra: dev
Requires-Dist: pytest; extra == "dev"
Requires-Dist: pytest-xdist; extra == "dev"
Requires-Dist: respx; extra == "dev"
Requires-Dist: ruff; extra == "dev"
Requires-Dist: nox; extra == "dev"
Requires-Dist: types-requests; extra == "dev"
Provides-Extra: docs
Requires-Dist: mkdocs; extra == "docs"
Requires-Dist: mkdocs-material; extra == "docs"
Requires-Dist: mkdocstrings[python]; extra == "docs"
